MANIFEST.in
README.md
setup.cfg
setup.py
boat/__init__.py
boat/boat.py
boat.egg-info/PKG-INFO
boat.egg-info/SOURCES.txt
boat.egg-info/dependency_links.txt
boat.egg-info/entry_points.txt
boat.egg-info/requires.txt
boat.egg-info/top_level.txt