Metadata-Version: 1.0
Name: boat
Version: 0.0.1
Summary: Instantly transfer files locally over HTTP
Home-page: https://github.com/ashisha/boat
Author: Ashish Anand
Author-email: UNKNOWN
License: MIT
Keywords: http,file,server,command line,cli
Platform: UNKNOWN
